{
    "data": [
        {
            "no_of_users": 10,
            "time": 1.0162370204925537,
            "speed": 9
        },
        {
            "no_of_users": 10,
            "time": 1.0835192203521729,
            "speed": 9
        }
    ],
    "rates": [
        [
            {
                "time_taken": 0.12385010719299316,
                "position": 1,
                "total_rate": "10"
            },
            {
                "time_taken": 0.22221088409423828,
                "position": 2,
                "total_rate": "10"
            },
            {
                "time_taken": 0.32090210914611816,
                "position": 3,
                "total_rate": "10"
            },
            {
                "time_taken": 0.4165339469909668,
                "position": 4,
                "total_rate": "10"
            },
            {
                "time_taken": 0.5107319355010986,
                "position": 5,
                "total_rate": "10"
            },
            {
                "time_taken": 0.609666109085083,
                "position": 6,
                "total_rate": "10"
            },
            {
                "time_taken": 0.705456018447876,
                "position": 7,
                "total_rate": "10"
            },
            {
                "time_taken": 0.8131039142608643,
                "position": 8,
                "total_rate": "10"
            },
            {
                "time_taken": 0.9079139232635498,
                "position": 9,
                "total_rate": "10"
            },
            {
                "time_taken": 1.0162279605865479,
                "position": 10,
                "total_rate": "10"
            }
        ],
        [
            {
                "time_taken": 0.11460113525390625,
                "position": 1,
                "total_rate": "10"
            },
            {
                "time_taken": 0.21863222122192383,
                "position": 2,
                "total_rate": "10"
            },
            {
                "time_taken": 0.3176591396331787,
                "position": 3,
                "total_rate": "10"
            },
            {
                "time_taken": 0.41243815422058105,
                "position": 4,
                "total_rate": "10"
            },
            {
                "time_taken": 0.5050640106201172,
                "position": 5,
                "total_rate": "10"
            },
            {
                "time_taken": 0.6193161010742188,
                "position": 6,
                "total_rate": "10"
            },
            {
                "time_taken": 0.7260580062866211,
                "position": 7,
                "total_rate": "10"
            },
            {
                "time_taken": 0.845405101776123,
                "position": 8,
                "total_rate": "10"
            },
            {
                "time_taken": 0.9828681945800781,
                "position": 9,
                "total_rate": "10"
            },
            {
                "time_taken": 1.0835092067718506,
                "position": 10,
                "total_rate": "10"
            }
        ]
    ]
}